SearchURL/__init__.py
SearchURL/main.py
SearchURL/vdb.py
SearchURL-1.1.4.dist-info/LICENCE
SearchURL-1.1.4.dist-info/METADATA
SearchURL-1.1.4.dist-info/WHEEL
SearchURL-1.1.4.dist-info/top_level.txt
SearchURL-1.1.4.dist-info/RECORD
