Metadata-Version: 2.1
Name: SearchURL
Version: 1.1.4
Summary: SearchURL lets perform Keyword, Fuzzy and Semantic Search through the text on websites using thier URLs.
Author: Pahul Gogna
Author-email: pahulgogna@gmail.com
License: MIT
Keywords: python,web-scraping,search,searchurl,SearchURL,Fuzzy matching,fuzzy search,web,scraping,semantic search,nlp,natural language processing
Classifier: Development Status :: 5 - Production/Stable
Classifier: Intended Audience :: Developers
Classifier: License :: OSI Approved :: MIT License
Classifier: Operating System :: OS Independent
Classifier: Programming Language :: Python :: 3.10
Classifier: Topic :: Text Processing :: Filters
Classifier: Topic :: Text Processing
Requires-Python: >=3.10
License-File: LICENCE
Requires-Dist: soupsieve>=2.6
Requires-Dist: beautifulsoup4>=4.12.3
Requires-Dist: requests
Requires-Dist: thefuzz>=0.22.1
Requires-Dist: chromadb>=0.5.11
Requires-Dist: sentence-transformers>=3.1.1
Provides-Extra: dev
Requires-Dist: twine>=4.0.2; extra == "dev"
